datetime_matcher/__init__.py
datetime_matcher/datetime_extractor.py
datetime_matcher/datetime_matcher.py
datetime_matcher/dfregex_lexer.py
datetime_matcher/model_types.py
datetime_matcher/py.typed
datetime_matcher/regex_generator.py
datetime_matcher-0.2.1.dist-info/LICENSE
datetime_matcher-0.2.1.dist-info/METADATA
datetime_matcher-0.2.1.dist-info/WHEEL
datetime_matcher-0.2.1.dist-info/top_level.txt
datetime_matcher-0.2.1.dist-info/RECORD
