Metadata-Version: 2.1
Name: datetime-matcher
Version: 0.2.1
Summary: A library which extends regex with support for datetime format codes.
Home-page: https://github.com/stephen-zhao/datetime_matcher
Author: Stephen Zhao
Author-email: mail@zhaostephen.com
License: UNKNOWN
Keywords: datetime,regex,datetime parsing,datetime format,substitution,regular expression,format,strftime,strptime,parse,reformat,date,time,format code,search,find,replace,match
Platform: UNKNOWN
Classifier: Development Status :: 3 - Alpha
Classifier: Intended Audience :: Developers
Classifier: Intended Audience :: System Administrators
Classifier: Programming Language :: Python :: 3
Classifier: License :: OSI Approved :: MIT License
Classifier: Natural Language :: English
Classifier: Operating System :: OS Independent
Classifier: Topic :: Software Development :: Libraries :: Python Modules
Classifier: Topic :: Text Processing
Classifier: Topic :: Utilities
Classifier: Typing :: Typed
Requires-Python: >=3.6
License-File: LICENSE
